MANIFEST.in
README.rst
setup.py
django_passwords.egg-info/PKG-INFO
django_passwords.egg-info/SOURCES.txt
django_passwords.egg-info/dependency_links.txt
django_passwords.egg-info/requires.txt
django_passwords.egg-info/top_level.txt
passwords/__init__.py
passwords/fields.py
passwords/models.py
passwords/validators.py
passwords/locale/bg/LC_MESSAGES/django.mo
passwords/locale/bg/LC_MESSAGES/django.po
passwords/locale/de/LC_MESSAGES/django.mo
passwords/locale/de/LC_MESSAGES/django.po
passwords/locale/en/LC_MESSAGES/django.mo
passwords/locale/en/LC_MESSAGES/django.po
passwords/locale/es/LC_MESSAGES/django.mo
passwords/locale/es/LC_MESSAGES/django.po
passwords/locale/es_AR/LC_MESSAGES/django.mo
passwords/locale/es_AR/LC_MESSAGES/django.po
passwords/locale/fr/LC_MESSAGES/django.mo
passwords/locale/fr/LC_MESSAGES/django.po
passwords/locale/ja/LC_MESSAGES/django.mo
passwords/locale/ja/LC_MESSAGES/django.po
passwords/locale/pl/LC_MESSAGES/django.mo
passwords/locale/pl/LC_MESSAGES/django.po
passwords/locale/pt_PT/LC_MESSAGES/django.mo
passwords/locale/pt_PT/LC_MESSAGES/django.po
passwords/locale/ru/LC_MESSAGES/django.mo
passwords/locale/ru/LC_MESSAGES/django.po
passwords/locale/tr/LC_MESSAGES/django.mo
passwords/locale/tr/LC_MESSAGES/django.po
passwords/locale/zh_CN/LC_MESSAGES/django.mo
passwords/locale/zh_CN/LC_MESSAGES/django.po