Metadata-Version: 1.1
Name: django-passwords
Version: 0.3.11
Summary: A Django reusable app that provides validators and a form field that checks the strength of a password
Home-page: http://github.com/dstufft/django-passwords/
Author: Donald Stufft
Author-email: donald@e.vilgeni.us
License: BSD
Platform: UNKNOWN
Classifier: Development Status :: 4 - Beta
Classifier: Environment :: Web Environment
Classifier: Intended Audience :: Developers
Classifier: License :: OSI Approved :: BSD License
Classifier: Operating System :: OS Independent
Classifier: Programming Language :: Python :: 2.6
Classifier: Programming Language :: Python :: 2.7
Classifier: Programming Language :: Python :: 3.4
Classifier: Programming Language :: Python :: 3.5
Classifier: Topic :: Utilities
Classifier: Framework :: Django
